[
    {
        "model": "myapp.product",
        "pk": 1,
        "fields": {
            "name": "Laptop",
            "price": "999.99",
            "description": "High-performance laptop"
        }
    },
    {
        "model": "myapp.product",
        "pk": 2,
        "fields": {
            "name": "Smartphone",
            "price": "599.99",
            "description": "Latest smartphone model"
        }
    },
    {
        "model": "myapp.product",
        "pk": 3,
        "fields": {
            "name": "Headphones",
            "price": "149.99",
            "description": "Noise-cancelling headphones"
        }
    }
]
